ogtfinder/__init__.py
ogtfinder/checks.py
ogtfinder/extractData.py
ogtfinder/ogtfinder.py
ogtfinder/data/AAdata.json
ogtfinder/data/mlp_rmse.pkl
ogtfinder-0.0.2.dist-info/METADATA
ogtfinder-0.0.2.dist-info/WHEEL
ogtfinder-0.0.2.dist-info/entry_points.txt
ogtfinder-0.0.2.dist-info/licenses/LICENSE
ogtfinder-0.0.2.dist-info/RECORD
