Metadata-Version: 2.4
Name: OGTFinder
Version: 0.0.2
Summary: OGTFinder is an optimal growth temperature prediction tool for prokaryotes using proteome-derived features
Project-URL: Homepage, https://github.com/SC-Git1/OGTFinder
License-Expression: MIT
License-File: LICENSE
Classifier: Intended Audience :: Science/Research
Classifier: License :: OSI Approved :: MIT License
Classifier: Operating System :: OS Independent
Classifier: Programming Language :: Python :: 3
Classifier: Topic :: Scientific/Engineering :: Bio-Informatics
Requires-Python: >=3.9
Requires-Dist: biopython>=1.84
Requires-Dist: numpy==2.0.0
Requires-Dist: pandas==2.2.2
Requires-Dist: scikit-learn==1.5.1
